rapidae/__init__.py
rapidae/conf.py
rapidae/data/__init__.py
rapidae/data/datasets.py
rapidae/data/preprocessing.py
rapidae/data/utils.py
rapidae/evaluate/__init__.py
rapidae/evaluate/cmapps_score.py
rapidae/evaluate/metric.py
rapidae/evaluate/utils.py
rapidae/models/__init__.py
rapidae/models/callbacks.py
rapidae/models/distributions.py
rapidae/models/utils.py
rapidae/models/ae/__init__.py
rapidae/models/ae/ae_model.py
rapidae/models/base/__init__.py
rapidae/models/base/base_architectures.py
rapidae/models/base/base_model.py
rapidae/models/base/default_architectures.py
rapidae/models/beta_vae/__init__.py
rapidae/models/beta_vae/beta_vae_model.py
rapidae/models/cae/__init__.py
rapidae/models/cae/cae_model.py
rapidae/models/rvae/__init__.py
rapidae/models/rvae/decoder.py
rapidae/models/rvae/encoder.py
rapidae/models/rvae/rvae_model.py
rapidae/models/rve/__init__.py
rapidae/models/rve/encoder.py
rapidae/models/rve/rve_model.py
rapidae/models/time_vae/__init__.py
rapidae/models/time_vae/decoder.py
rapidae/models/time_vae/encoder.py
rapidae/models/time_vae/time_vae_model.py
rapidae/models/vae/__init__.py
rapidae/models/vae/vae_model.py
rapidae/models/vq_vae/__init__.py
rapidae/models/vq_vae/decoder.py
rapidae/models/vq_vae/encoder.py
rapidae/models/vq_vae/vq_vae_model.py
rapidae/pipelines/__init__.py
rapidae/pipelines/base.py
rapidae/pipelines/evaluate.py
rapidae/pipelines/preprocess.py
rapidae/pipelines/training.py
rapidae-0.0.5.dist-info/METADATA
rapidae-0.0.5.dist-info/WHEEL
rapidae-0.0.5.dist-info/licenses/LICENSE
rapidae-0.0.5.dist-info/RECORD
