Metadata-Version: 2.4
Name: rapidae
Version: 0.0.5
Summary: Rapidae: Python Library for Rapid Creation and Experimentation of Autoencoders
Project-URL: Homepage, https://github.com/NahuelCostaCortez/rapidae
Project-URL: Issues, https://github.com/NahuelCostaCortez/rapidae/issues
Author-email: Nahuel Costa <costanahuel@gmail.com>, Lucas Pérez <lucasperezca22@gmail.com>
License-File: LICENSE
Keywords: autoencoder,deep learning,machine learning,variational autoencoder
Classifier: Intended Audience :: Science/Research
Classifier: License :: OSI Approved :: Apache Software License
Classifier: Operating System :: OS Independent
Classifier: Programming Language :: Python :: 3
Classifier: Topic :: Scientific/Engineering :: Artificial Intelligence
Requires-Python: <3.13,>=3.10
Requires-Dist: colorlog
Requires-Dist: keras>=3.0.1
Requires-Dist: matplotlib
Requires-Dist: numpy
Requires-Dist: pandas
Requires-Dist: requests
Requires-Dist: scikit-learn
